pycalculatrice/__init__.py
pycalculatrice/apps.py
pycalculatrice/operations.py
pycalculatrice/urls.py
pycalculatrice/views.py
pycalculatrice/templates/pycalculatrice/index.html
pycalculatrice-0.2.dist-info/METADATA
pycalculatrice-0.2.dist-info/WHEEL
pycalculatrice-0.2.dist-info/top_level.txt
pycalculatrice-0.2.dist-info/RECORD
